LICENSE
MANIFEST.in
requirements.txt
setup.py
todo.txt
django_gwo.egg-info/PKG-INFO
django_gwo.egg-info/SOURCES.txt
django_gwo.egg-info/dependency_links.txt
django_gwo.egg-info/requires.txt
django_gwo.egg-info/top_level.txt
doc_src/Makefile
doc_src/conf.py
doc_src/getting_started.rst
doc_src/index.rst
doc_src/installation.rst
doc_src/make.bat
doc_src/management_commands.rst
doc_src/overview.rst
doc_src/tutorial.rst
doc_src/using_gwoweboptimizer.rst
doc_src/_build/doctrees/environment.pickle
doc_src/_build/doctrees/getting_started.doctree
doc_src/_build/doctrees/index.doctree
doc_src/_build/doctrees/installation.doctree
doc_src/_build/doctrees/management_commands.doctree
doc_src/_build/doctrees/overview.doctree
doc_src/_build/doctrees/tutorial.doctree
doc_src/_build/doctrees/using_gwoweboptimizer.doctree
doc_src/_build/doctrees/reference/index.doctree
doc_src/_build/doctrees/reference/settings.doctree
doc_src/_build/doctrees/reference/websiteoptimizer/client.doctree
doc_src/_build/doctrees/reference/websiteoptimizer/data.doctree
doc_src/_build/doctrees/reference/websiteoptimizer/index.doctree
doc_src/_static/breadcrumb_background.png
doc_src/_static/default.css
doc_src/_static/documentation.png
doc_src/_static/header_sm_mid.png
doc_src/_static/scrn1.png
doc_src/_static/scrn2.png
doc_src/_static/searchfield_leftcap.png
doc_src/_static/searchfield_repeat.png
doc_src/_static/searchfield_rightcap.png
doc_src/_static/title_background.png
doc_src/_static/toc.js
doc_src/_static/triangle_closed.png
doc_src/_static/triangle_left.png
doc_src/_static/triangle_open.png
doc_src/_templates/layout.html
doc_src/reference/index.rst
doc_src/reference/settings.rst
doc_src/reference/websiteoptimizer/client.rst
doc_src/reference/websiteoptimizer/data.rst
doc_src/reference/websiteoptimizer/index.rst
docs/.buildinfo
docs/genindex.html
docs/getting_started.html
docs/index.html
docs/installation.html
docs/management_commands.html
docs/objects.inv
docs/overview.html
docs/py-modindex.html
docs/search.html
docs/searchindex.js
docs/tutorial.html
docs/using_gwoweboptimizer.html
docs/_sources/getting_started.txt
docs/_sources/index.txt
