Metadata-Version: 1.0
Name: django-gwo
Version: 0.4
Summary: Django driven Google Website Optimizer testing
Home-page: https://github.com/washingtontimes/django-gwo
Author: Corey Oordt
Author-email: coordt@washingtontimes.com
License: UNKNOWN
Platform: UNKNOWN
Classifier: License :: OSI Approved :: Apache Software License
Classifier: Framework :: Django
